grass/__init__.py
grass/function.py
grass/functor.py
grass_python-0.0.2.dist-info/LICENSE
grass_python-0.0.2.dist-info/METADATA
grass_python-0.0.2.dist-info/WHEEL
grass_python-0.0.2.dist-info/top_level.txt
grass_python-0.0.2.dist-info/RECORD
