Metadata-Version: 2.1
Name: grass-python
Version: 0.0.2
Summary: A small example package
Home-page: https://github.com/running-grass/grass-python
Author: ShiHua Liu
Author-email: au467195537@qq.com
License: UNKNOWN
Project-URL: Bug Tracker, https://github.com/running-grass/grass-python/issues
Platform: UNKNOWN
Classifier: Programming Language :: Python :: 3
Classifier: License :: OSI Approved :: MIT License
Classifier: Operating System :: OS Independent
Requires-Python: >=3.6
Requires-Dist: forbiddenfruit
